pyqt_svg_icon_text_widget/__init__.py
pyqt_svg_icon_text_widget/svgIconTextWidget.py
pyqt_svg_icon_text_widget-0.0.31.dist-info/LICENSE
pyqt_svg_icon_text_widget-0.0.31.dist-info/METADATA
pyqt_svg_icon_text_widget-0.0.31.dist-info/WHEEL
pyqt_svg_icon_text_widget-0.0.31.dist-info/top_level.txt
pyqt_svg_icon_text_widget-0.0.31.dist-info/RECORD
