Metadata-Version: 2.1
Name: pyqt-svg-icon-text-widget
Version: 0.0.31
Summary: PyQt widget consists of svg icon label and text label side by side
Home-page: https://github.com/yjg30737/pyqt-svg-icon-text-widget.git
Author: Jung Gyu Yoon
Author-email: yjg30737@gmail.com
License: MIT
License-File: LICENSE
Requires-Dist: PyQt5 (>=5.8)
Requires-Dist: pyqt-svg-label (>=0.0.1)
